setup.py
ymci.server.py
test/test_utils.py
ymci/__init__.py
ymci/config.py
ymci.egg-info/PKG-INFO
ymci.egg-info/SOURCES.txt
ymci.egg-info/dependency_links.txt
ymci.egg-info/requires.txt
ymci.egg-info/top_level.txt
ymci/builder/__init__.py
ymci/builder/util.py
ymci/ext/__init__.py
ymci/ext/db.py
ymci/ext/form.py
ymci/ext/hooks.py
ymci/ext/routes.py
ymci/model/__init__.py
ymci/routes/__init__.py
ymci/routes/admin.py
ymci/routes/blocks.py
ymci/routes/browse.py
ymci/routes/project.py
ymci/static/base.css
ymci/static/blocks.js
ymci/static/blocks.js.map
ymci/static/browse.js
ymci/static/browse.js.map
ymci/static/deps.min.js
ymci/static/deps.min.js.map
ymci/static/font.css
ymci/static/fonts
ymci/static/graph.js
ymci/static/graph.js.map
ymci/static/images
ymci/static/log.js
ymci/static/log.js.map
ymci/static/lumen-bootstrap.min.css
ymci/static/main.js
ymci/static/main.js.map
ymci/static/main.min.js
ymci/static/main.min.js.map
ymci/static/pygal-tooltips.js
ymci/static/svg.jquery.js
ymci/static/fonts/SourceCodePro-Bold.ttf.woff
ymci/static/fonts/SourceCodePro-Regular.ttf.woff
ymci/static/fonts/SourceCodePro-Semibold.ttf.woff
ymci/static/fonts/glyphicons-halflings-regular.eot
ymci/static/fonts/glyphicons-halflings-regular.svg
ymci/static/fonts/glyphicons-halflings-regular.ttf
ymci/static/fonts/glyphicons-halflings-regular.woff
ymci/static/images/favicon.png
ymci/templates/_base.html
ymci/templates/admin
ymci/templates/ask.html
ymci/templates/blocks
ymci/templates/error.html
ymci/templates/fields.html
ymci/templates/form.html
ymci/templates/index.html
ymci/templates/project
ymci/templates/source.html
ymci/templates/admin/index.html
ymci/templates/blocks/_base.html
ymci/templates/blocks/build.html
ymci/templates/blocks/history.html
ymci/templates/blocks/home.html
ymci/templates/blocks/plugins.html
ymci/templates/blocks/project.html
ymci/templates/project/list.html
ymci/templates/project/log.html
ymci/templates/project/view.html
ymci/utils/__init__.py
ymci/utils/db.py