Metadata-Version: 1.1
Name: ymci
Version: 0.1.4
Summary: Your Modern Continuous Integration server
Home-page: UNKNOWN
Author: Florian Mounier, Kozea
Author-email: florian.mounier@kozea.fr
License: UNKNOWN
Platform: Linux
Classifier: Development Status :: 3 - Alpha
Classifier: Environment :: Web Environment
Classifier: Intended Audience :: Developers
Classifier: Operating System :: POSIX :: Linux
Classifier: Programming Language :: Python :: 3
Classifier: Topic :: Software Development :: Build Tools
Provides: ymci
